{"cameraMode":{"drawMode":0,"name":"Shaded","section":"Shading Mode"},"sceneLighting":true,"audioPlay":false,"sceneViewState":{"m_AlwaysRefresh":false,"showFog":true,"showSkybox":true,"showFlares":true,"showImageEffects":true,"showParticleSystems":true,"showVisualEffectGraphs":true,"m_FxEnabled":true},"in2DMode":false,"pivot":{"x":-9.82225227355957,"y":-0.5752953290939331,"z":-5.177179336547852},"rotation":{"x":-0.012490144930779934,"y":0.7760403156280518,"z":-0.015374141745269299,"w":-0.6303818821907044},"size":14.448104858398438,"orthographic":false}